{"L1 (1477)": [{"timestamp": 1548302079, "avail": 60, "enroll": 0, "quota": 60, "wait": 0}, {"timestamp": 1548324241, "avail": 56, "enroll": 4, "quota": 60, "wait": 5}, {"timestamp": 1548325081, "avail": 36, "enroll": 24, "quota": 60, "wait": 13}, {"timestamp": 1548326041, "avail": 36, "enroll": 24, "quota": 60, "wait": 16}, {"timestamp": 1548326881, "avail": 36, "enroll": 24, "quota": 60, "wait": 17}, {"timestamp": 1548328680, "avail": 30, "enroll": 30, "quota": 60, "wait": 11}, {"timestamp": 1548329640, "avail": 30, "enroll": 30, "quota": 60, "wait": 13}, {"timestamp": 1548331441, "avail": 30, "enroll": 30, "quota": 60, "wait": 15}, {"timestamp": 1548332281, "avail": 26, "enroll": 34, "quota": 60, "wait": 12}, {"timestamp": 1548335881, "avail": 25, "enroll": 35, "quota": 60, "wait": 11}, {"timestamp": 1548338640, "avail": 25, "enroll": 35, "quota": 60, "wait": 12}, {"timestamp": 1548339481, "avail": 23, "enroll": 37, "quota": 60, "wait": 10}, {"timestamp": 1548351241, "avail": 24, "enroll": 36, "quota": 60, "wait": 10}, {"timestamp": 1548371041, "avail": 24, "enroll": 36, "quota": 60, "wait": 11}, {"timestamp": 1548380280, "avail": 23, "enroll": 37, "quota": 60, "wait": 10}, {"timestamp": 1548380281, "avail": 23, "enroll": 37, "quota": 60, "wait": 10}, {"timestamp": 1548381840, "avail": 23, "enroll": 37, "quota": 60, "wait": 11}, {"timestamp": 1548382680, "avail": 22, "enroll": 38, "quota": 60, "wait": 10}, {"timestamp": 1548389880, "avail": 21, "enroll": 39, "quota": 60, "wait": 10}, {"timestamp": 1548392641, "avail": 22, "enroll": 38, "quota": 60, "wait": 10}, {"timestamp": 1548393481, "avail": 21, "enroll": 39, "quota": 60, "wait": 10}, {"timestamp": 1548408841, "avail": 20, "enroll": 40, "quota": 60, "wait": 9}, {"timestamp": 1548438480, "avail": 21, "enroll": 39, "quota": 60, "wait": 9}, {"timestamp": 1548470881, "avail": 21, "enroll": 39, "quota": 60, "wait": 10}, {"timestamp": 1548472680, "avail": 20, "enroll": 40, "quota": 60, "wait": 9}, {"timestamp": 1548656280, "avail": 19, "enroll": 41, "quota": 60, "wait": 8}, {"timestamp": 1548661681, "avail": 19, "enroll": 41, "quota": 60, "wait": 8}, {"timestamp": 1548662640, "avail": 20, "enroll": 40, "quota": 60, "wait": 8}, {"timestamp": 1548716641, "avail": 20, "enroll": 40, "quota": 60, "wait": 9}, {"timestamp": 1548724681, "avail": 19, "enroll": 41, "quota": 60, "wait": 8}, {"timestamp": 1548726481, "avail": 19, "enroll": 41, "quota": 60, "wait": 9}, {"timestamp": 1548728280, "avail": 18, "enroll": 42, "quota": 60, "wait": 8}, {"timestamp": 1548729240, "avail": 18, "enroll": 42, "quota": 60, "wait": 9}, {"timestamp": 1548731880, "avail": 17, "enroll": 43, "quota": 60, "wait": 8}, {"timestamp": 1548735480, "avail": 16, "enroll": 44, "quota": 60, "wait": 8}, {"timestamp": 1548738240, "avail": 16, "enroll": 44, "quota": 60, "wait": 9}, {"timestamp": 1548739080, "avail": 15, "enroll": 45, "quota": 60, "wait": 8}, {"timestamp": 1548749040, "avail": 15, "enroll": 45, "quota": 60, "wait": 8}, {"timestamp": 1548760680, "avail": 14, "enroll": 46, "quota": 60, "wait": 7}, {"timestamp": 1548817440, "avail": 15, "enroll": 45, "quota": 60, "wait": 7}, {"timestamp": 1548821040, "avail": 16, "enroll": 44, "quota": 60, "wait": 6}, {"timestamp": 1548821880, "avail": 16, "enroll": 44, "quota": 60, "wait": 5}, {"timestamp": 1548827280, "avail": 17, "enroll": 43, "quota": 60, "wait": 5}, {"timestamp": 1548839880, "avail": 16, "enroll": 44, "quota": 60, "wait": 4}, {"timestamp": 1548917280, "avail": 16, "enroll": 44, "quota": 60, "wait": 5}, {"timestamp": 1548995640, "avail": 16, "enroll": 44, "quota": 60, "wait": 6}, {"timestamp": 1549036081, "avail": 16, "enroll": 44, "quota": 60, "wait": 7}, {"timestamp": 1549037880, "avail": 15, "enroll": 45, "quota": 60, "wait": 6}, {"timestamp": 1549248481, "avail": 15, "enroll": 45, "quota": 60, "wait": 5}]}