{"L1 (1155)": [{"timestamp": 1548302079, "avail": 60, "enroll": 0, "quota": 60, "wait": 0}, {"timestamp": 1548304440, "avail": 60, "enroll": 0, "quota": 60, "wait": 0}, {"timestamp": 1548312481, "avail": 60, "enroll": 0, "quota": 60, "wait": 0}, {"timestamp": 1548323281, "avail": 60, "enroll": 0, "quota": 60, "wait": 0}, {"timestamp": 1548324241, "avail": 56, "enroll": 4, "quota": 60, "wait": 0}, {"timestamp": 1548325081, "avail": 49, "enroll": 11, "quota": 60, "wait": 0}, {"timestamp": 1548326041, "avail": 48, "enroll": 12, "quota": 60, "wait": 0}, {"timestamp": 1548326881, "avail": 47, "enroll": 13, "quota": 60, "wait": 0}, {"timestamp": 1548327841, "avail": 46, "enroll": 14, "quota": 60, "wait": 0}, {"timestamp": 1548336841, "avail": 45, "enroll": 15, "quota": 60, "wait": 0}, {"timestamp": 1548380881, "avail": 44, "enroll": 16, "quota": 60, "wait": 0}, {"timestamp": 1548382680, "avail": 44, "enroll": 16, "quota": 60, "wait": 0}, {"timestamp": 1548596041, "avail": 43, "enroll": 17, "quota": 60, "wait": 0}, {"timestamp": 1548651841, "avail": 43, "enroll": 17, "quota": 60, "wait": 0}, {"timestamp": 1548657241, "avail": 44, "enroll": 16, "quota": 60, "wait": 0}, {"timestamp": 1548668041, "avail": 45, "enroll": 15, "quota": 60, "wait": 0}, {"timestamp": 1548749040, "avail": 45, "enroll": 15, "quota": 60, "wait": 0}, {"timestamp": 1548753480, "avail": 45, "enroll": 15, "quota": 60, "wait": 0}, {"timestamp": 1548760680, "avail": 46, "enroll": 14, "quota": 60, "wait": 0}, {"timestamp": 1548817440, "avail": 45, "enroll": 15, "quota": 60, "wait": 0}, {"timestamp": 1548821880, "avail": 44, "enroll": 16, "quota": 60, "wait": 0}, {"timestamp": 1548862440, "avail": 43, "enroll": 17, "quota": 60, "wait": 0}, {"timestamp": 1548866881, "avail": 42, "enroll": 18, "quota": 60, "wait": 0}, {"timestamp": 1548910080, "avail": 41, "enroll": 19, "quota": 60, "wait": 0}, {"timestamp": 1548999241, "avail": 42, "enroll": 18, "quota": 60, "wait": 0}, {"timestamp": 1549001881, "avail": 41, "enroll": 19, "quota": 60, "wait": 0}, {"timestamp": 1549003681, "avail": 40, "enroll": 20, "quota": 60, "wait": 0}, {"timestamp": 1549004640, "avail": 38, "enroll": 22, "quota": 60, "wait": 0}, {"timestamp": 1549008241, "avail": 35, "enroll": 25, "quota": 60, "wait": 0}, {"timestamp": 1549010040, "avail": 33, "enroll": 27, "quota": 60, "wait": 0}, {"timestamp": 1549012681, "avail": 32, "enroll": 28, "quota": 60, "wait": 0}, {"timestamp": 1549018081, "avail": 31, "enroll": 29, "quota": 60, "wait": 0}, {"timestamp": 1549027080, "avail": 30, "enroll": 30, "quota": 60, "wait": 0}, {"timestamp": 1549029841, "avail": 29, "enroll": 31, "quota": 60, "wait": 0}, {"timestamp": 1549040641, "avail": 28, "enroll": 32, "quota": 60, "wait": 0}, {"timestamp": 1549116241, "avail": 27, "enroll": 33, "quota": 60, "wait": 0}, {"timestamp": 1549122481, "avail": 26, "enroll": 34, "quota": 60, "wait": 0}, {"timestamp": 1549195440, "avail": 25, "enroll": 35, "quota": 60, "wait": 0}, {"timestamp": 1549613041, "avail": 25, "enroll": 35, "quota": 60, "wait": 0}, {"timestamp": 1549707961, "avail": 25, "enroll": 35, "quota": 60, "wait": 0}, {"timestamp": 1549850641, "avail": 26, "enroll": 34, "quota": 60, "wait": 0}, {"timestamp": 1549865881, "avail": 26, "enroll": 34, "quota": 60, "wait": 0}, {"timestamp": 1549867681, "avail": 25, "enroll": 35, "quota": 60, "wait": 0}, {"timestamp": 1549872240, "avail": 26, "enroll": 34, "quota": 60, "wait": 0}, {"timestamp": 1550045041, "avail": 25, "enroll": 35, "quota": 60, "wait": 0}, {"timestamp": 1550198880, "avail": 24, "enroll": 36, "quota": 60, "wait": 0}, {"timestamp": 1550199841, "avail": 23, "enroll": 37, "quota": 60, "wait": 0}]}