{"L1 (1136)": [{"timestamp": 1548302079, "avail": 20, "enroll": 0, "quota": 20, "wait": 0}, {"timestamp": 1548304440, "avail": 20, "enroll": 0, "quota": 20, "wait": 0}, {"timestamp": 1548312481, "avail": 20, "enroll": 0, "quota": 20, "wait": 0}, {"timestamp": 1548323281, "avail": 20, "enroll": 0, "quota": 20, "wait": 0}, {"timestamp": 1548324241, "avail": 14, "enroll": 6, "quota": 20, "wait": 2}, {"timestamp": 1548325081, "avail": 14, "enroll": 6, "quota": 20, "wait": 15}, {"timestamp": 1548326041, "avail": 3, "enroll": 17, "quota": 20, "wait": 4}, {"timestamp": 1548326881, "avail": 3, "enroll": 17, "quota": 20, "wait": 6}, {"timestamp": 1548328680, "avail": 1, "enroll": 19, "quota": 20, "wait": 4}, {"timestamp": 1548330481, "avail": 1, "enroll": 19, "quota": 20, "wait": 5}, {"timestamp": 1548332281, "avail": 0, "enroll": 20, "quota": 20, "wait": 4}, {"timestamp": 1548333241, "avail": 0, "enroll": 20, "quota": 20, "wait": 5}, {"timestamp": 1548344040, "avail": 0, "enroll": 20, "quota": 20, "wait": 4}, {"timestamp": 1548382680, "avail": 0, "enroll": 20, "quota": 20, "wait": 4}, {"timestamp": 1548391681, "avail": 0, "enroll": 20, "quota": 20, "wait": 5}, {"timestamp": 1548559080, "avail": 0, "enroll": 20, "quota": 20, "wait": 6}, {"timestamp": 1548651841, "avail": 0, "enroll": 20, "quota": 20, "wait": 6}, {"timestamp": 1548695881, "avail": 0, "enroll": 20, "quota": 20, "wait": 7}, {"timestamp": 1548735480, "avail": 0, "enroll": 20, "quota": 20, "wait": 8}, {"timestamp": 1548749040, "avail": 0, "enroll": 20, "quota": 20, "wait": 8}, {"timestamp": 1548753480, "avail": 0, "enroll": 20, "quota": 20, "wait": 8}, {"timestamp": 1548771480, "avail": 0, "enroll": 20, "quota": 20, "wait": 9}, {"timestamp": 1548841681, "avail": 0, "enroll": 20, "quota": 20, "wait": 8}, {"timestamp": 1548911040, "avail": 0, "enroll": 20, "quota": 20, "wait": 7}, {"timestamp": 1548924480, "avail": 0, "enroll": 20, "quota": 20, "wait": 6}, {"timestamp": 1548992880, "avail": 1, "enroll": 19, "quota": 20, "wait": 6}, {"timestamp": 1548994680, "avail": 0, "enroll": 20, "quota": 20, "wait": 5}, {"timestamp": 1549117081, "avail": 1, "enroll": 19, "quota": 20, "wait": 5}, {"timestamp": 1549118041, "avail": 0, "enroll": 20, "quota": 20, "wait": 4}, {"timestamp": 1549613041, "avail": 0, "enroll": 20, "quota": 20, "wait": 4}, {"timestamp": 1549707961, "avail": 0, "enroll": 20, "quota": 20, "wait": 4}, {"timestamp": 1549855080, "avail": 1, "enroll": 19, "quota": 20, "wait": 4}, {"timestamp": 1549856040, "avail": 1, "enroll": 19, "quota": 20, "wait": 5}, {"timestamp": 1549856880, "avail": 1, "enroll": 19, "quota": 20, "wait": 4}, {"timestamp": 1549865881, "avail": 1, "enroll": 19, "quota": 20, "wait": 4}, {"timestamp": 1550027880, "avail": 1, "enroll": 19, "quota": 20, "wait": 3}, {"timestamp": 1550048640, "avail": 2, "enroll": 18, "quota": 20, "wait": 3}, {"timestamp": 1550061240, "avail": 2, "enroll": 18, "quota": 20, "wait": 2}, {"timestamp": 1550161081, "avail": 0, "enroll": 20, "quota": 20, "wait": 2}, {"timestamp": 1550196240, "avail": 0, "enroll": 20, "quota": 20, "wait": 2}, {"timestamp": 1550253841, "avail": 0, "enroll": 20, "quota": 20, "wait": 0}]}