{"L1 (1133)": [{"timestamp": 1548302079, "avail": 20, "enroll": 0, "quota": 20, "wait": 0}, {"timestamp": 1548304440, "avail": 20, "enroll": 0, "quota": 20, "wait": 0}, {"timestamp": 1548312481, "avail": 20, "enroll": 0, "quota": 20, "wait": 0}, {"timestamp": 1548323281, "avail": 20, "enroll": 0, "quota": 20, "wait": 0}, {"timestamp": 1548324241, "avail": 19, "enroll": 1, "quota": 20, "wait": 5}, {"timestamp": 1548325081, "avail": 19, "enroll": 1, "quota": 20, "wait": 7}, {"timestamp": 1548326041, "avail": 14, "enroll": 6, "quota": 20, "wait": 2}, {"timestamp": 1548326881, "avail": 14, "enroll": 6, "quota": 20, "wait": 3}, {"timestamp": 1548328680, "avail": 13, "enroll": 7, "quota": 20, "wait": 2}, {"timestamp": 1548382680, "avail": 13, "enroll": 7, "quota": 20, "wait": 2}, {"timestamp": 1548407041, "avail": 13, "enroll": 7, "quota": 20, "wait": 2}, {"timestamp": 1548408841, "avail": 11, "enroll": 9, "quota": 20, "wait": 0}, {"timestamp": 1548496081, "avail": 10, "enroll": 10, "quota": 20, "wait": 0}, {"timestamp": 1548592440, "avail": 11, "enroll": 9, "quota": 20, "wait": 0}, {"timestamp": 1548651841, "avail": 11, "enroll": 9, "quota": 20, "wait": 0}, {"timestamp": 1548674280, "avail": 11, "enroll": 9, "quota": 20, "wait": 1}, {"timestamp": 1548690480, "avail": 12, "enroll": 8, "quota": 20, "wait": 1}, {"timestamp": 1548749040, "avail": 12, "enroll": 8, "quota": 20, "wait": 1}, {"timestamp": 1548752641, "avail": 12, "enroll": 8, "quota": 20, "wait": 2}, {"timestamp": 1548753480, "avail": 12, "enroll": 8, "quota": 20, "wait": 2}, {"timestamp": 1548754441, "avail": 11, "enroll": 9, "quota": 20, "wait": 1}, {"timestamp": 1548757080, "avail": 11, "enroll": 9, "quota": 20, "wait": 1}, {"timestamp": 1548758040, "avail": 10, "enroll": 10, "quota": 20, "wait": 0}, {"timestamp": 1548828241, "avail": 9, "enroll": 11, "quota": 20, "wait": 0}, {"timestamp": 1548845281, "avail": 8, "enroll": 12, "quota": 20, "wait": 0}, {"timestamp": 1548848040, "avail": 9, "enroll": 11, "quota": 20, "wait": 0}, {"timestamp": 1548985681, "avail": 10, "enroll": 10, "quota": 20, "wait": 0}, {"timestamp": 1549613041, "avail": 10, "enroll": 10, "quota": 20, "wait": 0}, {"timestamp": 1549707961, "avail": 10, "enroll": 10, "quota": 20, "wait": 0}, {"timestamp": 1549836240, "avail": 9, "enroll": 11, "quota": 20, "wait": 0}, {"timestamp": 1549865881, "avail": 9, "enroll": 11, "quota": 20, "wait": 0}, {"timestamp": 1549938841, "avail": 8, "enroll": 12, "quota": 20, "wait": 0}, {"timestamp": 1550161081, "avail": 6, "enroll": 14, "quota": 20, "wait": 0}, {"timestamp": 1550196240, "avail": 6, "enroll": 14, "quota": 20, "wait": 0}, {"timestamp": 1550197081, "avail": 5, "enroll": 15, "quota": 20, "wait": 0}]}