{"L1 (3670)": [{"timestamp": 1548302079, "avail": 53, "enroll": 12, "quota": 65, "wait": 0}, {"timestamp": 1548304440, "avail": 49, "enroll": 16, "quota": 65, "wait": 0}, {"timestamp": 1548305281, "avail": 48, "enroll": 17, "quota": 65, "wait": 0}, {"timestamp": 1548308041, "avail": 44, "enroll": 21, "quota": 65, "wait": 0}, {"timestamp": 1548312481, "avail": 44, "enroll": 21, "quota": 65, "wait": 0}, {"timestamp": 1548315241, "avail": 37, "enroll": 28, "quota": 65, "wait": 0}, {"timestamp": 1548318841, "avail": 31, "enroll": 34, "quota": 65, "wait": 0}, {"timestamp": 1548323281, "avail": 31, "enroll": 34, "quota": 65, "wait": 0}, {"timestamp": 1548345841, "avail": 30, "enroll": 35, "quota": 65, "wait": 0}, {"timestamp": 1548382680, "avail": 30, "enroll": 35, "quota": 65, "wait": 0}, {"timestamp": 1548386281, "avail": 26, "enroll": 39, "quota": 65, "wait": 0}, {"timestamp": 1548387241, "avail": 25, "enroll": 40, "quota": 65, "wait": 0}, {"timestamp": 1548388080, "avail": 24, "enroll": 41, "quota": 65, "wait": 0}, {"timestamp": 1548393481, "avail": 23, "enroll": 42, "quota": 65, "wait": 0}, {"timestamp": 1548407041, "avail": 22, "enroll": 43, "quota": 65, "wait": 0}, {"timestamp": 1548407880, "avail": 9, "enroll": 56, "quota": 65, "wait": 0}, {"timestamp": 1548408841, "avail": 4, "enroll": 61, "quota": 65, "wait": 0}, {"timestamp": 1548409681, "avail": 3, "enroll": 62, "quota": 65, "wait": 0}, {"timestamp": 1548553681, "avail": 2, "enroll": 63, "quota": 65, "wait": 0}, {"timestamp": 1548651841, "avail": 2, "enroll": 63, "quota": 65, "wait": 0}, {"timestamp": 1548670681, "avail": 1, "enroll": 64, "quota": 65, "wait": 0}, {"timestamp": 1548677041, "avail": 2, "enroll": 63, "quota": 65, "wait": 0}, {"timestamp": 1548687841, "avail": 0, "enroll": 65, "quota": 65, "wait": 0}, {"timestamp": 1548699480, "avail": 0, "enroll": 65, "quota": 65, "wait": 1}, {"timestamp": 1548718440, "avail": 0, "enroll": 65, "quota": 65, "wait": 2}, {"timestamp": 1548725641, "avail": 0, "enroll": 65, "quota": 65, "wait": 2}, {"timestamp": 1548735480, "avail": 0, "enroll": 65, "quota": 65, "wait": 3}, {"timestamp": 1548738240, "avail": 0, "enroll": 65, "quota": 65, "wait": 4}, {"timestamp": 1548746401, "avail": 0, "enroll": 65, "quota": 65, "wait": 5}, {"timestamp": 1548749040, "avail": 0, "enroll": 65, "quota": 65, "wait": 5}, {"timestamp": 1548753480, "avail": 0, "enroll": 65, "quota": 65, "wait": 5}, {"timestamp": 1548758040, "avail": 0, "enroll": 65, "quota": 65, "wait": 6}, {"timestamp": 1548833641, "avail": 0, "enroll": 65, "quota": 65, "wait": 5}, {"timestamp": 1548839880, "avail": 0, "enroll": 65, "quota": 65, "wait": 6}, {"timestamp": 1548840840, "avail": 1, "enroll": 64, "quota": 65, "wait": 6}, {"timestamp": 1548841681, "avail": 0, "enroll": 65, "quota": 65, "wait": 5}, {"timestamp": 1548900240, "avail": 0, "enroll": 65, "quota": 65, "wait": 6}, {"timestamp": 1548953280, "avail": 0, "enroll": 65, "quota": 65, "wait": 7}, {"timestamp": 1548993840, "avail": 0, "enroll": 65, "quota": 65, "wait": 6}, {"timestamp": 1549256640, "avail": 1, "enroll": 64, "quota": 65, "wait": 6}, {"timestamp": 1549258441, "avail": 0, "enroll": 65, "quota": 65, "wait": 5}, {"timestamp": 1549613041, "avail": 0, "enroll": 65, "quota": 65, "wait": 5}, {"timestamp": 1549707961, "avail": 0, "enroll": 65, "quota": 65, "wait": 5}]}