{"L1 (2511)": [{"timestamp": 1548302079, "avail": 20, "enroll": 60, "quota": 80, "wait": 0}, {"timestamp": 1548304440, "avail": 20, "enroll": 60, "quota": 80, "wait": 0}, {"timestamp": 1548305281, "avail": 20, "enroll": 60, "quota": 80, "wait": 0}, {"timestamp": 1548308041, "avail": 20, "enroll": 60, "quota": 80, "wait": 0}, {"timestamp": 1548308881, "avail": 20, "enroll": 60, "quota": 80, "wait": 0}, {"timestamp": 1548309840, "avail": 20, "enroll": 60, "quota": 80, "wait": 0}, {"timestamp": 1548311641, "avail": 19, "enroll": 61, "quota": 80, "wait": 0}, {"timestamp": 1548312481, "avail": 19, "enroll": 61, "quota": 80, "wait": 1}, {"timestamp": 1548315241, "avail": 18, "enroll": 62, "quota": 80, "wait": 0}, {"timestamp": 1548316081, "avail": 19, "enroll": 61, "quota": 80, "wait": 0}, {"timestamp": 1548317880, "avail": 19, "enroll": 61, "quota": 80, "wait": 0}, {"timestamp": 1548318841, "avail": 18, "enroll": 62, "quota": 80, "wait": 0}, {"timestamp": 1548319681, "avail": 18, "enroll": 62, "quota": 80, "wait": 0}, {"timestamp": 1548323281, "avail": 19, "enroll": 61, "quota": 80, "wait": 0}, {"timestamp": 1548382680, "avail": 19, "enroll": 61, "quota": 80, "wait": 0}, {"timestamp": 1548386281, "avail": 19, "enroll": 61, "quota": 80, "wait": 0}, {"timestamp": 1548390840, "avail": 18, "enroll": 62, "quota": 80, "wait": 0}, {"timestamp": 1548651841, "avail": 18, "enroll": 62, "quota": 80, "wait": 0}, {"timestamp": 1548725641, "avail": 18, "enroll": 62, "quota": 80, "wait": 0}, {"timestamp": 1548748080, "avail": 19, "enroll": 61, "quota": 80, "wait": 0}, {"timestamp": 1548749040, "avail": 19, "enroll": 61, "quota": 80, "wait": 0}, {"timestamp": 1548750840, "avail": 19, "enroll": 61, "quota": 80, "wait": 0}, {"timestamp": 1548753480, "avail": 19, "enroll": 61, "quota": 80, "wait": 0}, {"timestamp": 1548983881, "avail": 19, "enroll": 61, "quota": 80, "wait": 0}, {"timestamp": 1549599480, "avail": 19, "enroll": 61, "quota": 80, "wait": 0}, {"timestamp": 1549607641, "avail": 19, "enroll": 61, "quota": 80, "wait": 0}, {"timestamp": 1549613041, "avail": 19, "enroll": 61, "quota": 80, "wait": 0}, {"timestamp": 1549707961, "avail": 19, "enroll": 61, "quota": 80, "wait": 0}, {"timestamp": 1549865881, "avail": 19, "enroll": 61, "quota": 80, "wait": 0}, {"timestamp": 1549876681, "avail": 19, "enroll": 61, "quota": 80, "wait": 0}, {"timestamp": 1550030641, "avail": 19, "enroll": 61, "quota": 80, "wait": 0}, {"timestamp": 1550032440, "avail": 20, "enroll": 60, "quota": 80, "wait": 0}, {"timestamp": 1550196240, "avail": 20, "enroll": 60, "quota": 80, "wait": 0}, {"timestamp": 1550237640, "avail": 20, "enroll": 60, "quota": 80, "wait": 0}, {"timestamp": 1550240280, "avail": 21, "enroll": 59, "quota": 80, "wait": 0}], "T1 (2513)": [{"timestamp": 1548302079, "avail": 2, "enroll": 38, "quota": 40, "wait": 0}, {"timestamp": 1548304440, "avail": 2, "enroll": 38, "quota": 40, "wait": 0}, {"timestamp": 1548305281, "avail": 0, "enroll": 40, "quota": 40, "wait": 0}, {"timestamp": 1548308041, "avail": 1, "enroll": 39, "quota": 40, "wait": 0}, {"timestamp": 1548308881, "avail": 2, "enroll": 38, "quota": 40, "wait": 0}, {"timestamp": 1548309840, "avail": 1, "enroll": 39, "quota": 40, "wait": 0}, {"timestamp": 1548311641, "avail": 0, "enroll": 40, "quota": 40, "wait": 0}, {"timestamp": 1548312481, "avail": 1, "enroll": 39, "quota": 40, "wait": 1}, {"timestamp": 1548315241, "avail": 0, "enroll": 40, "quota": 40, "wait": 0}, {"timestamp": 1548316081, "avail": 1, "enroll": 39, "quota": 40, "wait": 0}, {"timestamp": 1548317880, "avail": 2, "enroll": 38, "quota": 40, "wait": 0}, {"timestamp": 1548318841, "avail": 2, "enroll": 38, "quota": 40, "wait": 0}, {"timestamp": 1548319681, "avail": 3, "enroll": 37, "quota": 40, "wait": 0}, {"timestamp": 1548323281, "avail": 3, "enroll": 37, "quota": 40, "wait": 0}, {"timestamp": 1548382680, "avail": 3, "enroll": 37, "quota": 40, "wait": 0}, {"timestamp": 1548386281, "avail": 3, "enroll": 37, "quota": 40, "wait": 0}, {"timestamp": 1548390840, "avail": 2, "enroll": 38, "quota": 40, "wait": 0}, {"timestamp": 1548651841, "avail": 2, "enroll": 38, "quota": 40, "wait": 0}, {"timestamp": 1548725641, "avail": 2, "enroll": 38, "quota": 40, "wait": 0}, {"timestamp": 1548748080, "avail": 2, "enroll": 38, "quota": 40, "wait": 0}, {"timestamp": 1548749040, "avail": 2, "enroll": 38, "quota": 40, "wait": 0}, {"timestamp": 1548750840, "avail": 1, "enroll": 39, "quota": 40, "wait": 0}, {"timestamp": 1548753480, "avail": 1, "enroll": 39, "quota": 40, "wait": 0}, {"timestamp": 1548983881, "avail": 1, "enroll": 39, "quota": 40, "wait": 0}, {"timestamp": 1549599480, "avail": 1, "enroll": 39, "quota": 40, "wait": 0}, {"timestamp": 1549607641, "avail": 1, "enroll": 39, "quota": 40, "wait": 0}, {"timestamp": 1549613041, "avail": 1, "enroll": 39, "quota": 40, "wait": 0}, {"timestamp": 1549707961, "avail": 1, "enroll": 39, "quota": 40, "wait": 0}, {"timestamp": 1549865881, "avail": 1, "enroll": 39, "quota": 40, "wait": 0}, {"timestamp": 1549876681, "avail": 1, "enroll": 39, "quota": 40, "wait": 0}, {"timestamp": 1550030641, "avail": 1, "enroll": 39, "quota": 40, "wait": 0}, {"timestamp": 1550032440, "avail": 1, "enroll": 39, "quota": 40, "wait": 0}, {"timestamp": 1550196240, "avail": 2, "enroll": 38, "quota": 40, "wait": 0}, {"timestamp": 1550237640, "avail": 1, "enroll": 39, "quota": 40, "wait": 0}, {"timestamp": 1550240280, "avail": 2, "enroll": 38, "quota": 40, "wait": 0}], "T2 (2515)": [{"timestamp": 1548302079, "avail": 18, "enroll": 22, "quota": 40, "wait": 0}, {"timestamp": 1548304440, "avail": 18, "enroll": 22, "quota": 40, "wait": 0}, {"timestamp": 1548305281, "avail": 20, "enroll": 20, "quota": 40, "wait": 0}, {"timestamp": 1548308041, "avail": 19, "enroll": 21, "quota": 40, "wait": 0}, {"timestamp": 1548308881, "avail": 18, "enroll": 22, "quota": 40, "wait": 0}, {"timestamp": 1548309840, "avail": 19, "enroll": 21, "quota": 40, "wait": 0}, {"timestamp": 1548311641, "avail": 19, "enroll": 21, "quota": 40, "wait": 0}, {"timestamp": 1548312481, "avail": 18, "enroll": 22, "quota": 40, "wait": 0}, {"timestamp": 1548315241, "avail": 18, "enroll": 22, "quota": 40, "wait": 0}, {"timestamp": 1548316081, "avail": 18, "enroll": 22, "quota": 40, "wait": 0}, {"timestamp": 1548317880, "avail": 17, "enroll": 23, "quota": 40, "wait": 0}, {"timestamp": 1548318841, "avail": 16, "enroll": 24, "quota": 40, "wait": 0}, {"timestamp": 1548319681, "avail": 15, "enroll": 25, "quota": 40, "wait": 0}, {"timestamp": 1548323281, "avail": 16, "enroll": 24, "quota": 40, "wait": 0}, {"timestamp": 1548382680, "avail": 16, "enroll": 24, "quota": 40, "wait": 0}, {"timestamp": 1548386281, "avail": 16, "enroll": 24, "quota": 40, "wait": 0}, {"timestamp": 1548390840, "avail": 16, "enroll": 24, "quota": 40, "wait": 0}, {"timestamp": 1548651841, "avail": 16, "enroll": 24, "quota": 40, "wait": 0}, {"timestamp": 1548725641, "avail": 16, "enroll": 24, "quota": 40, "wait": 0}, {"timestamp": 1548748080, "avail": 17, "enroll": 23, "quota": 40, "wait": 0}, {"timestamp": 1548749040, "avail": 17, "enroll": 23, "quota": 40, "wait": 0}, {"timestamp": 1548750840, "avail": 18, "enroll": 22, "quota": 40, "wait": 0}, {"timestamp": 1548753480, "avail": 18, "enroll": 22, "quota": 40, "wait": 0}, {"timestamp": 1548983881, "avail": 18, "enroll": 22, "quota": 40, "wait": 0}, {"timestamp": 1549599480, "avail": 18, "enroll": 22, "quota": 40, "wait": 0}, {"timestamp": 1549607641, "avail": 18, "enroll": 22, "quota": 40, "wait": 0}, {"timestamp": 1549613041, "avail": 18, "enroll": 22, "quota": 40, "wait": 0}, {"timestamp": 1549707961, "avail": 18, "enroll": 22, "quota": 40, "wait": 0}, {"timestamp": 1549865881, "avail": 18, "enroll": 22, "quota": 40, "wait": 0}, {"timestamp": 1549876681, "avail": 18, "enroll": 22, "quota": 40, "wait": 0}, {"timestamp": 1550030641, "avail": 18, "enroll": 22, "quota": 40, "wait": 0}, {"timestamp": 1550032440, "avail": 19, "enroll": 21, "quota": 40, "wait": 0}, {"timestamp": 1550196240, "avail": 18, "enroll": 22, "quota": 40, "wait": 0}, {"timestamp": 1550237640, "avail": 19, "enroll": 21, "quota": 40, "wait": 0}, {"timestamp": 1550240280, "avail": 19, "enroll": 21, "quota": 40, "wait": 0}]}