{"L1 (3934)": [{"timestamp": 1548302079, "avail": 10, "enroll": 0, "quota": 10, "wait": 0}, {"timestamp": 1548304440, "avail": 10, "enroll": 0, "quota": 10, "wait": 0}, {"timestamp": 1548312481, "avail": 10, "enroll": 0, "quota": 10, "wait": 0}, {"timestamp": 1548323281, "avail": 10, "enroll": 0, "quota": 10, "wait": 0}, {"timestamp": 1548382680, "avail": 10, "enroll": 0, "quota": 10, "wait": 0}, {"timestamp": 1548386281, "avail": 10, "enroll": 0, "quota": 10, "wait": 0}, {"timestamp": 1548640081, "avail": 9, "enroll": 1, "quota": 10, "wait": 0}, {"timestamp": 1548642840, "avail": 8, "enroll": 2, "quota": 10, "wait": 0}, {"timestamp": 1548650041, "avail": 7, "enroll": 3, "quota": 10, "wait": 0}, {"timestamp": 1548651841, "avail": 7, "enroll": 3, "quota": 10, "wait": 0}, {"timestamp": 1548703080, "avail": 6, "enroll": 4, "quota": 10, "wait": 0}, {"timestamp": 1548725641, "avail": 6, "enroll": 4, "quota": 10, "wait": 0}, {"timestamp": 1548739080, "avail": 5, "enroll": 5, "quota": 10, "wait": 0}, {"timestamp": 1548749040, "avail": 5, "enroll": 5, "quota": 10, "wait": 0}, {"timestamp": 1548753480, "avail": 5, "enroll": 5, "quota": 10, "wait": 0}, {"timestamp": 1548767041, "avail": 4, "enroll": 6, "quota": 10, "wait": 0}, {"timestamp": 1548838081, "avail": 4, "enroll": 6, "quota": 10, "wait": 0}, {"timestamp": 1548912841, "avail": 2, "enroll": 8, "quota": 10, "wait": 0}, {"timestamp": 1548983881, "avail": 2, "enroll": 8, "quota": 10, "wait": 0}, {"timestamp": 1549013640, "avail": 3, "enroll": 7, "quota": 10, "wait": 0}, {"timestamp": 1549016281, "avail": 2, "enroll": 8, "quota": 10, "wait": 0}, {"timestamp": 1549105441, "avail": 1, "enroll": 9, "quota": 10, "wait": 0}, {"timestamp": 1549599480, "avail": 1, "enroll": 9, "quota": 10, "wait": 0}, {"timestamp": 1549607641, "avail": 1, "enroll": 9, "quota": 10, "wait": 0}, {"timestamp": 1549613041, "avail": 1, "enroll": 9, "quota": 10, "wait": 0}], "LA1 (3935)": [{"timestamp": 1548302079, "avail": 10, "enroll": 0, "quota": 10, "wait": 0}, {"timestamp": 1548304440, "avail": 10, "enroll": 0, "quota": 10, "wait": 0}, {"timestamp": 1548312481, "avail": 10, "enroll": 0, "quota": 10, "wait": 0}, {"timestamp": 1548323281, "avail": 10, "enroll": 0, "quota": 10, "wait": 0}, {"timestamp": 1548382680, "avail": 10, "enroll": 0, "quota": 10, "wait": 0}, {"timestamp": 1548386281, "avail": 10, "enroll": 0, "quota": 10, "wait": 0}, {"timestamp": 1548640081, "avail": 9, "enroll": 1, "quota": 10, "wait": 0}, {"timestamp": 1548642840, "avail": 8, "enroll": 2, "quota": 10, "wait": 0}, {"timestamp": 1548650041, "avail": 7, "enroll": 3, "quota": 10, "wait": 0}, {"timestamp": 1548651841, "avail": 7, "enroll": 3, "quota": 10, "wait": 0}, {"timestamp": 1548703080, "avail": 6, "enroll": 4, "quota": 10, "wait": 0}, {"timestamp": 1548725641, "avail": 6, "enroll": 4, "quota": 10, "wait": 0}, {"timestamp": 1548739080, "avail": 5, "enroll": 5, "quota": 10, "wait": 0}, {"timestamp": 1548749040, "avail": 5, "enroll": 5, "quota": 10, "wait": 0}, {"timestamp": 1548753480, "avail": 5, "enroll": 5, "quota": 10, "wait": 0}, {"timestamp": 1548767041, "avail": 4, "enroll": 6, "quota": 10, "wait": 0}, {"timestamp": 1548838081, "avail": 4, "enroll": 6, "quota": 10, "wait": 0}, {"timestamp": 1548912841, "avail": 2, "enroll": 8, "quota": 10, "wait": 0}, {"timestamp": 1548983881, "avail": 2, "enroll": 8, "quota": 10, "wait": 0}, {"timestamp": 1549013640, "avail": 3, "enroll": 7, "quota": 10, "wait": 0}, {"timestamp": 1549016281, "avail": 2, "enroll": 8, "quota": 10, "wait": 0}, {"timestamp": 1549105441, "avail": 1, "enroll": 9, "quota": 10, "wait": 0}, {"timestamp": 1549599480, "avail": 1, "enroll": 9, "quota": 10, "wait": 0}, {"timestamp": 1549607641, "avail": 1, "enroll": 9, "quota": 10, "wait": 0}, {"timestamp": 1549613041, "avail": 1, "enroll": 9, "quota": 10, "wait": 0}]}