{"L1 (3358)": [{"timestamp": 1548302079, "avail": 2, "enroll": 42, "quota": 44, "wait": 0}, {"timestamp": 1548304440, "avail": 2, "enroll": 42, "quota": 44, "wait": 0}, {"timestamp": 1548305281, "avail": 1, "enroll": 43, "quota": 44, "wait": 0}, {"timestamp": 1548308041, "avail": 1, "enroll": 43, "quota": 44, "wait": 2}, {"timestamp": 1548308881, "avail": 0, "enroll": 44, "quota": 44, "wait": 3}, {"timestamp": 1548309840, "avail": 1, "enroll": 43, "quota": 44, "wait": 2}, {"timestamp": 1548311641, "avail": 3, "enroll": 41, "quota": 44, "wait": 2}, {"timestamp": 1548312481, "avail": 3, "enroll": 41, "quota": 44, "wait": 5}, {"timestamp": 1548315241, "avail": 2, "enroll": 42, "quota": 44, "wait": 4}, {"timestamp": 1548316081, "avail": 2, "enroll": 42, "quota": 44, "wait": 8}, {"timestamp": 1548317041, "avail": 2, "enroll": 42, "quota": 44, "wait": 8}, {"timestamp": 1548318841, "avail": 4, "enroll": 40, "quota": 44, "wait": 8}, {"timestamp": 1548319681, "avail": 4, "enroll": 40, "quota": 44, "wait": 10}, {"timestamp": 1548320641, "avail": 5, "enroll": 39, "quota": 44, "wait": 10}, {"timestamp": 1548322441, "avail": 0, "enroll": 44, "quota": 44, "wait": 5}, {"timestamp": 1548323281, "avail": 0, "enroll": 44, "quota": 44, "wait": 5}, {"timestamp": 1548327841, "avail": 0, "enroll": 44, "quota": 44, "wait": 6}, {"timestamp": 1548328680, "avail": 1, "enroll": 43, "quota": 44, "wait": 5}, {"timestamp": 1548329640, "avail": 0, "enroll": 44, "quota": 44, "wait": 4}, {"timestamp": 1548335041, "avail": 3, "enroll": 41, "quota": 44, "wait": 4}, {"timestamp": 1548336841, "avail": 1, "enroll": 43, "quota": 44, "wait": 2}, {"timestamp": 1548343081, "avail": 1, "enroll": 43, "quota": 44, "wait": 3}, {"timestamp": 1548344040, "avail": 0, "enroll": 44, "quota": 44, "wait": 2}, {"timestamp": 1548380280, "avail": 1, "enroll": 43, "quota": 44, "wait": 2}, {"timestamp": 1548380281, "avail": 1, "enroll": 43, "quota": 44, "wait": 2}, {"timestamp": 1548382680, "avail": 1, "enroll": 43, "quota": 44, "wait": 2}, {"timestamp": 1548383641, "avail": 1, "enroll": 43, "quota": 44, "wait": 3}, {"timestamp": 1548386281, "avail": 1, "enroll": 43, "quota": 44, "wait": 4}, {"timestamp": 1548387241, "avail": 0, "enroll": 44, "quota": 44, "wait": 4}, {"timestamp": 1548389041, "avail": 0, "enroll": 44, "quota": 44, "wait": 4}, {"timestamp": 1548390840, "avail": 0, "enroll": 44, "quota": 44, "wait": 5}, {"timestamp": 1548398041, "avail": 0, "enroll": 44, "quota": 44, "wait": 6}, {"timestamp": 1548403440, "avail": 0, "enroll": 44, "quota": 44, "wait": 6}, {"timestamp": 1548407880, "avail": 0, "enroll": 44, "quota": 44, "wait": 7}, {"timestamp": 1548409681, "avail": 0, "enroll": 44, "quota": 44, "wait": 8}, {"timestamp": 1548415081, "avail": 0, "enroll": 44, "quota": 44, "wait": 9}, {"timestamp": 1548416881, "avail": 0, "enroll": 44, "quota": 44, "wait": 9}, {"timestamp": 1548467280, "avail": 1, "enroll": 43, "quota": 44, "wait": 8}, {"timestamp": 1548470040, "avail": 0, "enroll": 44, "quota": 44, "wait": 7}, {"timestamp": 1548651841, "avail": 0, "enroll": 44, "quota": 44, "wait": 7}, {"timestamp": 1548677041, "avail": 0, "enroll": 44, "quota": 44, "wait": 7}, {"timestamp": 1548689641, "avail": 0, "enroll": 44, "quota": 44, "wait": 8}, {"timestamp": 1548725641, "avail": 0, "enroll": 44, "quota": 44, "wait": 8}, {"timestamp": 1548730080, "avail": 0, "enroll": 44, "quota": 44, "wait": 8}, {"timestamp": 1548745440, "avail": 0, "enroll": 44, "quota": 44, "wait": 8}, {"timestamp": 1548747240, "avail": 0, "enroll": 44, "quota": 44, "wait": 8}, {"timestamp": 1548749040, "avail": 0, "enroll": 44, "quota": 44, "wait": 8}, {"timestamp": 1548753480, "avail": 0, "enroll": 44, "quota": 44, "wait": 8}, {"timestamp": 1548832681, "avail": 0, "enroll": 44, "quota": 44, "wait": 8}, {"timestamp": 1548833641, "avail": 0, "enroll": 44, "quota": 44, "wait": 8}, {"timestamp": 1548901080, "avail": 0, "enroll": 44, "quota": 44, "wait": 8}, {"timestamp": 1548913681, "avail": 0, "enroll": 44, "quota": 44, "wait": 5}, {"timestamp": 1548983881, "avail": 0, "enroll": 44, "quota": 44, "wait": 5}, {"timestamp": 1548995640, "avail": 0, "enroll": 44, "quota": 44, "wait": 5}, {"timestamp": 1549018081, "avail": 0, "enroll": 44, "quota": 44, "wait": 5}, {"timestamp": 1549288080, "avail": 0, "enroll": 44, "quota": 44, "wait": 4}, {"timestamp": 1549341240, "avail": 0, "enroll": 44, "quota": 44, "wait": 3}, {"timestamp": 1549361880, "avail": 0, "enroll": 44, "quota": 44, "wait": 2}, {"timestamp": 1549599480, "avail": 0, "enroll": 44, "quota": 44, "wait": 2}, {"timestamp": 1549607641, "avail": 0, "enroll": 44, "quota": 44, "wait": 2}, {"timestamp": 1549613041, "avail": 0, "enroll": 44, "quota": 44, "wait": 2}, {"timestamp": 1549707961, "avail": 0, "enroll": 44, "quota": 44, "wait": 2}], "L2 (3360)": [{"timestamp": 1548302079, "avail": 0, "enroll": 43, "quota": 43, "wait": 3}, {"timestamp": 1548304440, "avail": 0, "enroll": 43, "quota": 43, "wait": 3}, {"timestamp": 1548305281, "avail": 0, "enroll": 43, "quota": 43, "wait": 4}, {"timestamp": 1548308041, "avail": 0, "enroll": 43, "quota": 43, "wait": 4}, {"timestamp": 1548308881, "avail": 1, "enroll": 42, "quota": 43, "wait": 5}, {"timestamp": 1548309840, "avail": 2, "enroll": 41, "quota": 43, "wait": 5}, {"timestamp": 1548311641, "avail": 1, "enroll": 42, "quota": 43, "wait": 3}, {"timestamp": 1548312481, "avail": 2, "enroll": 41, "quota": 43, "wait": 3}, {"timestamp": 1548315241, "avail": 1, "enroll": 42, "quota": 43, "wait": 2}, {"timestamp": 1548316081, "avail": 4, "enroll": 39, "quota": 43, "wait": 6}, {"timestamp": 1548317041, "avail": 4, "enroll": 39, "quota": 43, "wait": 6}, {"timestamp": 1548318841, "avail": 0, "enroll": 43, "quota": 43, "wait": 2}, {"timestamp": 1548319681, "avail": 1, "enroll": 42, "quota": 43, "wait": 3}, {"timestamp": 1548320641, "avail": 2, "enroll": 41, "quota": 43, "wait": 3}, {"timestamp": 1548322441, "avail": 3, "enroll": 40, "quota": 43, "wait": 0}, {"timestamp": 1548323281, "avail": 3, "enroll": 40, "quota": 43, "wait": 0}, {"timestamp": 1548327841, "avail": 3, "enroll": 40, "quota": 43, "wait": 0}, {"timestamp": 1548328680, "avail": 3, "enroll": 40, "quota": 43, "wait": 0}, {"timestamp": 1548329640, "avail": 4, "enroll": 39, "quota": 43, "wait": 0}, {"timestamp": 1548335041, "avail": 2, "enroll": 41, "quota": 43, "wait": 0}, {"timestamp": 1548336841, "avail": 3, "enroll": 40, "quota": 43, "wait": 0}, {"timestamp": 1548343081, "avail": 3, "enroll": 40, "quota": 43, "wait": 0}, {"timestamp": 1548344040, "avail": 4, "enroll": 39, "quota": 43, "wait": 0}, {"timestamp": 1548380280, "avail": 4, "enroll": 39, "quota": 43, "wait": 0}, {"timestamp": 1548380281, "avail": 4, "enroll": 39, "quota": 43, "wait": 0}, {"timestamp": 1548382680, "avail": 4, "enroll": 39, "quota": 43, "wait": 0}, {"timestamp": 1548383641, "avail": 4, "enroll": 39, "quota": 43, "wait": 0}, {"timestamp": 1548386281, "avail": 4, "enroll": 39, "quota": 43, "wait": 0}, {"timestamp": 1548387241, "avail": 4, "enroll": 39, "quota": 43, "wait": 0}, {"timestamp": 1548389041, "avail": 4, "enroll": 39, "quota": 43, "wait": 0}, {"timestamp": 1548390840, "avail": 4, "enroll": 39, "quota": 43, "wait": 0}, {"timestamp": 1548398041, "avail": 4, "enroll": 39, "quota": 43, "wait": 0}, {"timestamp": 1548403440, "avail": 3, "enroll": 40, "quota": 43, "wait": 0}, {"timestamp": 1548407880, "avail": 3, "enroll": 40, "quota": 43, "wait": 0}, {"timestamp": 1548409681, "avail": 3, "enroll": 40, "quota": 43, "wait": 0}, {"timestamp": 1548415081, "avail": 3, "enroll": 40, "quota": 43, "wait": 0}, {"timestamp": 1548416881, "avail": 4, "enroll": 39, "quota": 43, "wait": 0}, {"timestamp": 1548467280, "avail": 2, "enroll": 41, "quota": 43, "wait": 0}, {"timestamp": 1548470040, "avail": 2, "enroll": 41, "quota": 43, "wait": 0}, {"timestamp": 1548651841, "avail": 2, "enroll": 41, "quota": 43, "wait": 0}, {"timestamp": 1548677041, "avail": 3, "enroll": 40, "quota": 43, "wait": 0}, {"timestamp": 1548689641, "avail": 3, "enroll": 40, "quota": 43, "wait": 0}, {"timestamp": 1548725641, "avail": 3, "enroll": 40, "quota": 43, "wait": 0}, {"timestamp": 1548730080, "avail": 3, "enroll": 40, "quota": 43, "wait": 0}, {"timestamp": 1548745440, "avail": 3, "enroll": 40, "quota": 43, "wait": 0}, {"timestamp": 1548747240, "avail": 3, "enroll": 40, "quota": 43, "wait": 0}, {"timestamp": 1548749040, "avail": 3, "enroll": 40, "quota": 43, "wait": 0}, {"timestamp": 1548753480, "avail": 3, "enroll": 40, "quota": 43, "wait": 0}, {"timestamp": 1548832681, "avail": 1, "enroll": 42, "quota": 43, "wait": 0}, {"timestamp": 1548833641, "avail": 0, "enroll": 43, "quota": 43, "wait": 0}, {"timestamp": 1548901080, "avail": 0, "enroll": 43, "quota": 43, "wait": 0}, {"timestamp": 1548913681, "avail": 0, "enroll": 43, "quota": 43, "wait": 0}, {"timestamp": 1548983881, "avail": 0, "enroll": 43, "quota": 43, "wait": 0}, {"timestamp": 1548995640, "avail": 0, "enroll": 43, "quota": 43, "wait": 0}, {"timestamp": 1549018081, "avail": 0, "enroll": 43, "quota": 43, "wait": 1}, {"timestamp": 1549288080, "avail": 0, "enroll": 43, "quota": 43, "wait": 1}, {"timestamp": 1549341240, "avail": 0, "enroll": 43, "quota": 43, "wait": 1}, {"timestamp": 1549361880, "avail": 0, "enroll": 43, "quota": 43, "wait": 1}, {"timestamp": 1549599480, "avail": 0, "enroll": 43, "quota": 43, "wait": 1}, {"timestamp": 1549607641, "avail": 0, "enroll": 43, "quota": 43, "wait": 1}, {"timestamp": 1549613041, "avail": 0, "enroll": 43, "quota": 43, "wait": 1}, {"timestamp": 1549707961, "avail": 0, "enroll": 43, "quota": 43, "wait": 1}], "L3 (3362)": [{"timestamp": 1548302079, "avail": 6, "enroll": 37, "quota": 43, "wait": 0}, {"timestamp": 1548304440, "avail": 6, "enroll": 37, "quota": 43, "wait": 0}, {"timestamp": 1548305281, "avail": 7, "enroll": 36, "quota": 43, "wait": 0}, {"timestamp": 1548308041, "avail": 7, "enroll": 36, "quota": 43, "wait": 0}, {"timestamp": 1548308881, "avail": 7, "enroll": 36, "quota": 43, "wait": 0}, {"timestamp": 1548309840, "avail": 5, "enroll": 38, "quota": 43, "wait": 0}, {"timestamp": 1548311641, "avail": 5, "enroll": 38, "quota": 43, "wait": 0}, {"timestamp": 1548312481, "avail": 4, "enroll": 39, "quota": 43, "wait": 0}, {"timestamp": 1548315241, "avail": 6, "enroll": 37, "quota": 43, "wait": 0}, {"timestamp": 1548316081, "avail": 3, "enroll": 40, "quota": 43, "wait": 0}, {"timestamp": 1548317041, "avail": 3, "enroll": 40, "quota": 43, "wait": 0}, {"timestamp": 1548318841, "avail": 5, "enroll": 38, "quota": 43, "wait": 0}, {"timestamp": 1548319681, "avail": 4, "enroll": 39, "quota": 43, "wait": 0}, {"timestamp": 1548320641, "avail": 3, "enroll": 40, "quota": 43, "wait": 0}, {"timestamp": 1548322441, "avail": 7, "enroll": 36, "quota": 43, "wait": 0}, {"timestamp": 1548323281, "avail": 7, "enroll": 36, "quota": 43, "wait": 0}, {"timestamp": 1548327841, "avail": 7, "enroll": 36, "quota": 43, "wait": 0}, {"timestamp": 1548328680, "avail": 6, "enroll": 37, "quota": 43, "wait": 0}, {"timestamp": 1548329640, "avail": 6, "enroll": 37, "quota": 43, "wait": 0}, {"timestamp": 1548335041, "avail": 5, "enroll": 38, "quota": 43, "wait": 0}, {"timestamp": 1548336841, "avail": 6, "enroll": 37, "quota": 43, "wait": 0}, {"timestamp": 1548343081, "avail": 6, "enroll": 37, "quota": 43, "wait": 0}, {"timestamp": 1548344040, "avail": 6, "enroll": 37, "quota": 43, "wait": 0}, {"timestamp": 1548380280, "avail": 7, "enroll": 36, "quota": 43, "wait": 0}, {"timestamp": 1548380281, "avail": 7, "enroll": 36, "quota": 43, "wait": 0}, {"timestamp": 1548382680, "avail": 7, "enroll": 36, "quota": 43, "wait": 0}, {"timestamp": 1548383641, "avail": 7, "enroll": 36, "quota": 43, "wait": 0}, {"timestamp": 1548386281, "avail": 7, "enroll": 36, "quota": 43, "wait": 0}, {"timestamp": 1548387241, "avail": 7, "enroll": 36, "quota": 43, "wait": 0}, {"timestamp": 1548389041, "avail": 6, "enroll": 37, "quota": 43, "wait": 0}, {"timestamp": 1548390840, "avail": 6, "enroll": 37, "quota": 43, "wait": 0}, {"timestamp": 1548398041, "avail": 6, "enroll": 37, "quota": 43, "wait": 0}, {"timestamp": 1548403440, "avail": 7, "enroll": 36, "quota": 43, "wait": 0}, {"timestamp": 1548407880, "avail": 7, "enroll": 36, "quota": 43, "wait": 0}, {"timestamp": 1548409681, "avail": 7, "enroll": 36, "quota": 43, "wait": 0}, {"timestamp": 1548415081, "avail": 7, "enroll": 36, "quota": 43, "wait": 0}, {"timestamp": 1548416881, "avail": 6, "enroll": 37, "quota": 43, "wait": 0}, {"timestamp": 1548467280, "avail": 7, "enroll": 36, "quota": 43, "wait": 0}, {"timestamp": 1548470040, "avail": 7, "enroll": 36, "quota": 43, "wait": 0}, {"timestamp": 1548651841, "avail": 7, "enroll": 36, "quota": 43, "wait": 0}, {"timestamp": 1548677041, "avail": 6, "enroll": 37, "quota": 43, "wait": 0}, {"timestamp": 1548689641, "avail": 6, "enroll": 37, "quota": 43, "wait": 0}, {"timestamp": 1548725641, "avail": 6, "enroll": 37, "quota": 43, "wait": 0}, {"timestamp": 1548730080, "avail": 7, "enroll": 36, "quota": 43, "wait": 0}, {"timestamp": 1548745440, "avail": 7, "enroll": 36, "quota": 43, "wait": 0}, {"timestamp": 1548747240, "avail": 7, "enroll": 36, "quota": 43, "wait": 0}, {"timestamp": 1548749040, "avail": 7, "enroll": 36, "quota": 43, "wait": 0}, {"timestamp": 1548753480, "avail": 7, "enroll": 36, "quota": 43, "wait": 0}, {"timestamp": 1548832681, "avail": 7, "enroll": 36, "quota": 43, "wait": 0}, {"timestamp": 1548833641, "avail": 7, "enroll": 36, "quota": 43, "wait": 0}, {"timestamp": 1548901080, "avail": 7, "enroll": 36, "quota": 43, "wait": 0}, {"timestamp": 1548913681, "avail": 4, "enroll": 39, "quota": 43, "wait": 0}, {"timestamp": 1548983881, "avail": 4, "enroll": 39, "quota": 43, "wait": 0}, {"timestamp": 1548995640, "avail": 4, "enroll": 39, "quota": 43, "wait": 0}, {"timestamp": 1549018081, "avail": 4, "enroll": 39, "quota": 43, "wait": 0}, {"timestamp": 1549288080, "avail": 4, "enroll": 39, "quota": 43, "wait": 0}, {"timestamp": 1549341240, "avail": 4, "enroll": 39, "quota": 43, "wait": 0}, {"timestamp": 1549361880, "avail": 4, "enroll": 39, "quota": 43, "wait": 0}, {"timestamp": 1549599480, "avail": 4, "enroll": 39, "quota": 43, "wait": 0}, {"timestamp": 1549607641, "avail": 4, "enroll": 39, "quota": 43, "wait": 0}, {"timestamp": 1549613041, "avail": 4, "enroll": 39, "quota": 43, "wait": 0}, {"timestamp": 1549707961, "avail": 4, "enroll": 39, "quota": 43, "wait": 0}], "LA1 (3394)": [{"timestamp": 1548302079, "avail": 2, "enroll": 42, "quota": 44, "wait": 0}, {"timestamp": 1548304440, "avail": 2, "enroll": 42, "quota": 44, "wait": 0}, {"timestamp": 1548305281, "avail": 1, "enroll": 43, "quota": 44, "wait": 0}, {"timestamp": 1548308041, "avail": 1, "enroll": 43, "quota": 44, "wait": 2}, {"timestamp": 1548308881, "avail": 0, "enroll": 44, "quota": 44, "wait": 3}, {"timestamp": 1548309840, "avail": 1, "enroll": 43, "quota": 44, "wait": 2}, {"timestamp": 1548311641, "avail": 3, "enroll": 41, "quota": 44, "wait": 2}, {"timestamp": 1548312481, "avail": 3, "enroll": 41, "quota": 44, "wait": 5}, {"timestamp": 1548315241, "avail": 2, "enroll": 42, "quota": 44, "wait": 4}, {"timestamp": 1548316081, "avail": 2, "enroll": 42, "quota": 44, "wait": 8}, {"timestamp": 1548317041, "avail": 2, "enroll": 42, "quota": 44, "wait": 8}, {"timestamp": 1548318841, "avail": 4, "enroll": 40, "quota": 44, "wait": 8}, {"timestamp": 1548319681, "avail": 4, "enroll": 40, "quota": 44, "wait": 10}, {"timestamp": 1548320641, "avail": 5, "enroll": 39, "quota": 44, "wait": 10}, {"timestamp": 1548322441, "avail": 0, "enroll": 44, "quota": 44, "wait": 5}, {"timestamp": 1548323281, "avail": 0, "enroll": 44, "quota": 44, "wait": 5}, {"timestamp": 1548327841, "avail": 0, "enroll": 44, "quota": 44, "wait": 6}, {"timestamp": 1548328680, "avail": 1, "enroll": 43, "quota": 44, "wait": 5}, {"timestamp": 1548329640, "avail": 0, "enroll": 44, "quota": 44, "wait": 4}, {"timestamp": 1548335041, "avail": 3, "enroll": 41, "quota": 44, "wait": 4}, {"timestamp": 1548336841, "avail": 1, "enroll": 43, "quota": 44, "wait": 2}, {"timestamp": 1548343081, "avail": 1, "enroll": 43, "quota": 44, "wait": 3}, {"timestamp": 1548344040, "avail": 0, "enroll": 44, "quota": 44, "wait": 2}, {"timestamp": 1548380280, "avail": 1, "enroll": 43, "quota": 44, "wait": 2}, {"timestamp": 1548380281, "avail": 1, "enroll": 43, "quota": 44, "wait": 2}, {"timestamp": 1548382680, "avail": 1, "enroll": 43, "quota": 44, "wait": 2}, {"timestamp": 1548383641, "avail": 1, "enroll": 43, "quota": 44, "wait": 3}, {"timestamp": 1548386281, "avail": 1, "enroll": 43, "quota": 44, "wait": 4}, {"timestamp": 1548387241, "avail": 0, "enroll": 44, "quota": 44, "wait": 4}, {"timestamp": 1548389041, "avail": 0, "enroll": 44, "quota": 44, "wait": 4}, {"timestamp": 1548390840, "avail": 0, "enroll": 44, "quota": 44, "wait": 5}, {"timestamp": 1548398041, "avail": 0, "enroll": 44, "quota": 44, "wait": 6}, {"timestamp": 1548403440, "avail": 0, "enroll": 44, "quota": 44, "wait": 6}, {"timestamp": 1548407880, "avail": 0, "enroll": 44, "quota": 44, "wait": 7}, {"timestamp": 1548409681, "avail": 0, "enroll": 44, "quota": 44, "wait": 8}, {"timestamp": 1548415081, "avail": 0, "enroll": 44, "quota": 44, "wait": 9}, {"timestamp": 1548416881, "avail": 0, "enroll": 44, "quota": 44, "wait": 9}, {"timestamp": 1548467280, "avail": 1, "enroll": 43, "quota": 44, "wait": 8}, {"timestamp": 1548470040, "avail": 0, "enroll": 44, "quota": 44, "wait": 7}, {"timestamp": 1548651841, "avail": 0, "enroll": 44, "quota": 44, "wait": 7}, {"timestamp": 1548677041, "avail": 0, "enroll": 44, "quota": 44, "wait": 7}, {"timestamp": 1548689641, "avail": 0, "enroll": 44, "quota": 44, "wait": 8}, {"timestamp": 1548725641, "avail": 0, "enroll": 44, "quota": 44, "wait": 8}, {"timestamp": 1548730080, "avail": 0, "enroll": 44, "quota": 44, "wait": 8}, {"timestamp": 1548745440, "avail": 0, "enroll": 44, "quota": 44, "wait": 8}, {"timestamp": 1548747240, "avail": 0, "enroll": 44, "quota": 44, "wait": 8}, {"timestamp": 1548749040, "avail": 0, "enroll": 44, "quota": 44, "wait": 8}, {"timestamp": 1548753480, "avail": 0, "enroll": 44, "quota": 44, "wait": 8}, {"timestamp": 1548832681, "avail": 0, "enroll": 44, "quota": 44, "wait": 8}, {"timestamp": 1548833641, "avail": 0, "enroll": 44, "quota": 44, "wait": 8}, {"timestamp": 1548901080, "avail": 0, "enroll": 44, "quota": 44, "wait": 8}, {"timestamp": 1548913681, "avail": 0, "enroll": 44, "quota": 44, "wait": 5}, {"timestamp": 1548983881, "avail": 0, "enroll": 44, "quota": 44, "wait": 5}, {"timestamp": 1548995640, "avail": 0, "enroll": 44, "quota": 44, "wait": 5}, {"timestamp": 1549018081, "avail": 0, "enroll": 44, "quota": 44, "wait": 5}, {"timestamp": 1549288080, "avail": 0, "enroll": 44, "quota": 44, "wait": 4}, {"timestamp": 1549341240, "avail": 0, "enroll": 44, "quota": 44, "wait": 3}, {"timestamp": 1549361880, "avail": 0, "enroll": 44, "quota": 44, "wait": 2}, {"timestamp": 1549599480, "avail": 0, "enroll": 44, "quota": 44, "wait": 2}, {"timestamp": 1549607641, "avail": 0, "enroll": 44, "quota": 44, "wait": 2}, {"timestamp": 1549613041, "avail": 0, "enroll": 44, "quota": 44, "wait": 2}, {"timestamp": 1549707961, "avail": 0, "enroll": 44, "quota": 44, "wait": 2}], "LA2 (3396)": [{"timestamp": 1548302079, "avail": 0, "enroll": 43, "quota": 43, "wait": 3}, {"timestamp": 1548304440, "avail": 0, "enroll": 43, "quota": 43, "wait": 3}, {"timestamp": 1548305281, "avail": 0, "enroll": 43, "quota": 43, "wait": 4}, {"timestamp": 1548308041, "avail": 0, "enroll": 43, "quota": 43, "wait": 4}, {"timestamp": 1548308881, "avail": 1, "enroll": 42, "quota": 43, "wait": 5}, {"timestamp": 1548309840, "avail": 2, "enroll": 41, "quota": 43, "wait": 5}, {"timestamp": 1548311641, "avail": 1, "enroll": 42, "quota": 43, "wait": 3}, {"timestamp": 1548312481, "avail": 2, "enroll": 41, "quota": 43, "wait": 3}, {"timestamp": 1548315241, "avail": 1, "enroll": 42, "quota": 43, "wait": 2}, {"timestamp": 1548316081, "avail": 4, "enroll": 39, "quota": 43, "wait": 6}, {"timestamp": 1548317041, "avail": 4, "enroll": 39, "quota": 43, "wait": 6}, {"timestamp": 1548318841, "avail": 0, "enroll": 43, "quota": 43, "wait": 2}, {"timestamp": 1548319681, "avail": 1, "enroll": 42, "quota": 43, "wait": 3}, {"timestamp": 1548320641, "avail": 2, "enroll": 41, "quota": 43, "wait": 3}, {"timestamp": 1548322441, "avail": 3, "enroll": 40, "quota": 43, "wait": 0}, {"timestamp": 1548323281, "avail": 3, "enroll": 40, "quota": 43, "wait": 0}, {"timestamp": 1548327841, "avail": 3, "enroll": 40, "quota": 43, "wait": 0}, {"timestamp": 1548328680, "avail": 3, "enroll": 40, "quota": 43, "wait": 0}, {"timestamp": 1548329640, "avail": 4, "enroll": 39, "quota": 43, "wait": 0}, {"timestamp": 1548335041, "avail": 2, "enroll": 41, "quota": 43, "wait": 0}, {"timestamp": 1548336841, "avail": 3, "enroll": 40, "quota": 43, "wait": 0}, {"timestamp": 1548343081, "avail": 3, "enroll": 40, "quota": 43, "wait": 0}, {"timestamp": 1548344040, "avail": 4, "enroll": 39, "quota": 43, "wait": 0}, {"timestamp": 1548380280, "avail": 4, "enroll": 39, "quota": 43, "wait": 0}, {"timestamp": 1548380281, "avail": 4, "enroll": 39, "quota": 43, "wait": 0}, {"timestamp": 1548382680, "avail": 4, "enroll": 39, "quota": 43, "wait": 0}, {"timestamp": 1548383641, "avail": 4, "enroll": 39, "quota": 43, "wait": 0}, {"timestamp": 1548386281, "avail": 4, "enroll": 39, "quota": 43, "wait": 0}, {"timestamp": 1548387241, "avail": 4, "enroll": 39, "quota": 43, "wait": 0}, {"timestamp": 1548389041, "avail": 4, "enroll": 39, "quota": 43, "wait": 0}, {"timestamp": 1548390840, "avail": 4, "enroll": 39, "quota": 43, "wait": 0}, {"timestamp": 1548398041, "avail": 4, "enroll": 39, "quota": 43, "wait": 0}, {"timestamp": 1548403440, "avail": 3, "enroll": 40, "quota": 43, "wait": 0}, {"timestamp": 1548407880, "avail": 3, "enroll": 40, "quota": 43, "wait": 0}, {"timestamp": 1548409681, "avail": 3, "enroll": 40, "quota": 43, "wait": 0}, {"timestamp": 1548415081, "avail": 3, "enroll": 40, "quota": 43, "wait": 0}, {"timestamp": 1548416881, "avail": 4, "enroll": 39, "quota": 43, "wait": 0}, {"timestamp": 1548467280, "avail": 2, "enroll": 41, "quota": 43, "wait": 0}, {"timestamp": 1548470040, "avail": 2, "enroll": 41, "quota": 43, "wait": 0}, {"timestamp": 1548651841, "avail": 2, "enroll": 41, "quota": 43, "wait": 0}, {"timestamp": 1548677041, "avail": 3, "enroll": 40, "quota": 43, "wait": 0}, {"timestamp": 1548689641, "avail": 3, "enroll": 40, "quota": 43, "wait": 0}, {"timestamp": 1548725641, "avail": 3, "enroll": 40, "quota": 43, "wait": 0}, {"timestamp": 1548730080, "avail": 3, "enroll": 40, "quota": 43, "wait": 0}, {"timestamp": 1548745440, "avail": 3, "enroll": 40, "quota": 43, "wait": 0}, {"timestamp": 1548747240, "avail": 3, "enroll": 40, "quota": 43, "wait": 0}, {"timestamp": 1548749040, "avail": 3, "enroll": 40, "quota": 43, "wait": 0}, {"timestamp": 1548753480, "avail": 3, "enroll": 40, "quota": 43, "wait": 0}, {"timestamp": 1548832681, "avail": 1, "enroll": 42, "quota": 43, "wait": 0}, {"timestamp": 1548833641, "avail": 0, "enroll": 43, "quota": 43, "wait": 0}, {"timestamp": 1548901080, "avail": 0, "enroll": 43, "quota": 43, "wait": 0}, {"timestamp": 1548913681, "avail": 0, "enroll": 43, "quota": 43, "wait": 0}, {"timestamp": 1548983881, "avail": 0, "enroll": 43, "quota": 43, "wait": 0}, {"timestamp": 1548995640, "avail": 0, "enroll": 43, "quota": 43, "wait": 0}, {"timestamp": 1549018081, "avail": 0, "enroll": 43, "quota": 43, "wait": 1}, {"timestamp": 1549288080, "avail": 0, "enroll": 43, "quota": 43, "wait": 1}, {"timestamp": 1549341240, "avail": 0, "enroll": 43, "quota": 43, "wait": 1}, {"timestamp": 1549361880, "avail": 0, "enroll": 43, "quota": 43, "wait": 1}, {"timestamp": 1549599480, "avail": 0, "enroll": 43, "quota": 43, "wait": 1}, {"timestamp": 1549607641, "avail": 0, "enroll": 43, "quota": 43, "wait": 1}, {"timestamp": 1549613041, "avail": 0, "enroll": 43, "quota": 43, "wait": 1}, {"timestamp": 1549707961, "avail": 0, "enroll": 43, "quota": 43, "wait": 1}], "LA3 (3397)": [{"timestamp": 1548302079, "avail": 6, "enroll": 37, "quota": 43, "wait": 0}, {"timestamp": 1548304440, "avail": 6, "enroll": 37, "quota": 43, "wait": 0}, {"timestamp": 1548305281, "avail": 7, "enroll": 36, "quota": 43, "wait": 0}, {"timestamp": 1548308041, "avail": 7, "enroll": 36, "quota": 43, "wait": 0}, {"timestamp": 1548308881, "avail": 7, "enroll": 36, "quota": 43, "wait": 0}, {"timestamp": 1548309840, "avail": 5, "enroll": 38, "quota": 43, "wait": 0}, {"timestamp": 1548311641, "avail": 5, "enroll": 38, "quota": 43, "wait": 0}, {"timestamp": 1548312481, "avail": 4, "enroll": 39, "quota": 43, "wait": 0}, {"timestamp": 1548315241, "avail": 6, "enroll": 37, "quota": 43, "wait": 0}, {"timestamp": 1548316081, "avail": 3, "enroll": 40, "quota": 43, "wait": 0}, {"timestamp": 1548317041, "avail": 3, "enroll": 40, "quota": 43, "wait": 0}, {"timestamp": 1548318841, "avail": 5, "enroll": 38, "quota": 43, "wait": 0}, {"timestamp": 1548319681, "avail": 4, "enroll": 39, "quota": 43, "wait": 0}, {"timestamp": 1548320641, "avail": 3, "enroll": 40, "quota": 43, "wait": 0}, {"timestamp": 1548322441, "avail": 7, "enroll": 36, "quota": 43, "wait": 0}, {"timestamp": 1548323281, "avail": 7, "enroll": 36, "quota": 43, "wait": 0}, {"timestamp": 1548327841, "avail": 7, "enroll": 36, "quota": 43, "wait": 0}, {"timestamp": 1548328680, "avail": 6, "enroll": 37, "quota": 43, "wait": 0}, {"timestamp": 1548329640, "avail": 6, "enroll": 37, "quota": 43, "wait": 0}, {"timestamp": 1548335041, "avail": 5, "enroll": 38, "quota": 43, "wait": 0}, {"timestamp": 1548336841, "avail": 6, "enroll": 37, "quota": 43, "wait": 0}, {"timestamp": 1548343081, "avail": 6, "enroll": 37, "quota": 43, "wait": 0}, {"timestamp": 1548344040, "avail": 6, "enroll": 37, "quota": 43, "wait": 0}, {"timestamp": 1548380280, "avail": 7, "enroll": 36, "quota": 43, "wait": 0}, {"timestamp": 1548380281, "avail": 7, "enroll": 36, "quota": 43, "wait": 0}, {"timestamp": 1548382680, "avail": 7, "enroll": 36, "quota": 43, "wait": 0}, {"timestamp": 1548383641, "avail": 7, "enroll": 36, "quota": 43, "wait": 0}, {"timestamp": 1548386281, "avail": 7, "enroll": 36, "quota": 43, "wait": 0}, {"timestamp": 1548387241, "avail": 7, "enroll": 36, "quota": 43, "wait": 0}, {"timestamp": 1548389041, "avail": 6, "enroll": 37, "quota": 43, "wait": 0}, {"timestamp": 1548390840, "avail": 6, "enroll": 37, "quota": 43, "wait": 0}, {"timestamp": 1548398041, "avail": 6, "enroll": 37, "quota": 43, "wait": 0}, {"timestamp": 1548403440, "avail": 7, "enroll": 36, "quota": 43, "wait": 0}, {"timestamp": 1548407880, "avail": 7, "enroll": 36, "quota": 43, "wait": 0}, {"timestamp": 1548409681, "avail": 7, "enroll": 36, "quota": 43, "wait": 0}, {"timestamp": 1548415081, "avail": 7, "enroll": 36, "quota": 43, "wait": 0}, {"timestamp": 1548416881, "avail": 6, "enroll": 37, "quota": 43, "wait": 0}, {"timestamp": 1548467280, "avail": 7, "enroll": 36, "quota": 43, "wait": 0}, {"timestamp": 1548470040, "avail": 7, "enroll": 36, "quota": 43, "wait": 0}, {"timestamp": 1548651841, "avail": 7, "enroll": 36, "quota": 43, "wait": 0}, {"timestamp": 1548677041, "avail": 6, "enroll": 37, "quota": 43, "wait": 0}, {"timestamp": 1548689641, "avail": 6, "enroll": 37, "quota": 43, "wait": 0}, {"timestamp": 1548725641, "avail": 6, "enroll": 37, "quota": 43, "wait": 0}, {"timestamp": 1548730080, "avail": 7, "enroll": 36, "quota": 43, "wait": 0}, {"timestamp": 1548745440, "avail": 7, "enroll": 36, "quota": 43, "wait": 0}, {"timestamp": 1548747240, "avail": 7, "enroll": 36, "quota": 43, "wait": 0}, {"timestamp": 1548749040, "avail": 7, "enroll": 36, "quota": 43, "wait": 0}, {"timestamp": 1548753480, "avail": 7, "enroll": 36, "quota": 43, "wait": 0}, {"timestamp": 1548832681, "avail": 7, "enroll": 36, "quota": 43, "wait": 0}, {"timestamp": 1548833641, "avail": 7, "enroll": 36, "quota": 43, "wait": 0}, {"timestamp": 1548901080, "avail": 7, "enroll": 36, "quota": 43, "wait": 0}, {"timestamp": 1548913681, "avail": 4, "enroll": 39, "quota": 43, "wait": 0}, {"timestamp": 1548983881, "avail": 4, "enroll": 39, "quota": 43, "wait": 0}, {"timestamp": 1548995640, "avail": 4, "enroll": 39, "quota": 43, "wait": 0}, {"timestamp": 1549018081, "avail": 4, "enroll": 39, "quota": 43, "wait": 0}, {"timestamp": 1549288080, "avail": 4, "enroll": 39, "quota": 43, "wait": 0}, {"timestamp": 1549341240, "avail": 4, "enroll": 39, "quota": 43, "wait": 0}, {"timestamp": 1549361880, "avail": 4, "enroll": 39, "quota": 43, "wait": 0}, {"timestamp": 1549599480, "avail": 4, "enroll": 39, "quota": 43, "wait": 0}, {"timestamp": 1549607641, "avail": 4, "enroll": 39, "quota": 43, "wait": 0}, {"timestamp": 1549613041, "avail": 4, "enroll": 39, "quota": 43, "wait": 0}, {"timestamp": 1549707961, "avail": 4, "enroll": 39, "quota": 43, "wait": 0}]}