{"LA1 (4009)": [{"timestamp": 1548992040, "avail": 1, "enroll": 0, "quota": 1, "wait": 0}, {"timestamp": 1548995640, "avail": 1, "enroll": 0, "quota": 1, "wait": 0}, {"timestamp": 1549012681, "avail": 1, "enroll": 0, "quota": 1, "wait": 0}, {"timestamp": 1549176480, "avail": 0, "enroll": 1, "quota": 1, "wait": 0}, {"timestamp": 1549597681, "avail": 0, "enroll": 1, "quota": 1, "wait": 0}, {"timestamp": 1549599480, "avail": 0, "enroll": 1, "quota": 1, "wait": 0}, {"timestamp": 1549607641, "avail": 0, "enroll": 1, "quota": 1, "wait": 0}, {"timestamp": 1549613041, "avail": 0, "enroll": 1, "quota": 1, "wait": 0}, {"timestamp": 1549707961, "avail": 0, "enroll": 1, "quota": 1, "wait": 0}, {"timestamp": 1549847881, "avail": 0, "enroll": 1, "quota": 1, "wait": 0}, {"timestamp": 1549865881, "avail": 0, "enroll": 1, "quota": 1, "wait": 0}, {"timestamp": 1549876681, "avail": 0, "enroll": 1, "quota": 1, "wait": 0}, {"timestamp": 1550027041, "avail": 0, "enroll": 1, "quota": 1, "wait": 0}, {"timestamp": 1550030641, "avail": 0, "enroll": 1, "quota": 1, "wait": 0}, {"timestamp": 1550045041, "avail": 0, "enroll": 1, "quota": 1, "wait": 0}, {"timestamp": 1550050441, "avail": 0, "enroll": 1, "quota": 1, "wait": 0}, {"timestamp": 1550196240, "avail": 0, "enroll": 1, "quota": 1, "wait": 0}, {"timestamp": 1550205240, "avail": 0, "enroll": 1, "quota": 1, "wait": 0}, {"timestamp": 1550217840, "avail": 0, "enroll": 1, "quota": 1, "wait": 0}], "LA2 (4010)": [{"timestamp": 1548992040, "avail": 1, "enroll": 0, "quota": 1, "wait": 0}, {"timestamp": 1548995640, "avail": 1, "enroll": 0, "quota": 1, "wait": 0}, {"timestamp": 1549012681, "avail": 0, "enroll": 1, "quota": 1, "wait": 0}, {"timestamp": 1549176480, "avail": 0, "enroll": 1, "quota": 1, "wait": 0}, {"timestamp": 1549597681, "avail": 0, "enroll": 1, "quota": 1, "wait": 0}, {"timestamp": 1549599480, "avail": 0, "enroll": 1, "quota": 1, "wait": 0}, {"timestamp": 1549607641, "avail": 0, "enroll": 1, "quota": 1, "wait": 0}, {"timestamp": 1549613041, "avail": 0, "enroll": 1, "quota": 1, "wait": 0}, {"timestamp": 1549707961, "avail": 0, "enroll": 1, "quota": 1, "wait": 0}, {"timestamp": 1549847881, "avail": 0, "enroll": 1, "quota": 1, "wait": 0}, {"timestamp": 1549865881, "avail": 0, "enroll": 1, "quota": 1, "wait": 0}, {"timestamp": 1549876681, "avail": 0, "enroll": 1, "quota": 1, "wait": 0}, {"timestamp": 1550027041, "avail": 0, "enroll": 1, "quota": 1, "wait": 0}, {"timestamp": 1550030641, "avail": 0, "enroll": 1, "quota": 1, "wait": 0}, {"timestamp": 1550045041, "avail": 0, "enroll": 1, "quota": 1, "wait": 0}, {"timestamp": 1550050441, "avail": 0, "enroll": 1, "quota": 1, "wait": 0}, {"timestamp": 1550196240, "avail": 0, "enroll": 1, "quota": 1, "wait": 0}, {"timestamp": 1550205240, "avail": 0, "enroll": 1, "quota": 1, "wait": 0}, {"timestamp": 1550217840, "avail": 0, "enroll": 1, "quota": 1, "wait": 0}]}